napari_update_checker/__init__.py
napari_update_checker/_version.py
napari_update_checker/napari.yaml
napari_update_checker/qt_update_checker.py
napari_update_checker/utils.py
napari_update_checker/_tests/__init__.py
napari_update_checker/_tests/test_qt_update_checker.py
napari_update_checker/_tests/test_utils.py
napari_update_checker-0.1.0.dist-info/LICENSE.txt
napari_update_checker-0.1.0.dist-info/METADATA
napari_update_checker-0.1.0.dist-info/WHEEL
napari_update_checker-0.1.0.dist-info/entry_points.txt
napari_update_checker-0.1.0.dist-info/top_level.txt
napari_update_checker-0.1.0.dist-info/RECORD
